<useCase id="UC1">
    <name>Enable Step Counter Feature</name>
    <actors>
        <actor>Social Caregiver</actor>
        <actor>User</actor>
    </actors>
    <mainSequence>
        <step id="S1">Caregiver Requests to Enable Step Counter feature for User</step>
        <step id="S2">Alfred Activates Step Counter</step>
        <step id="S3">User Receives Message: "Step Counter feature is now available."</step>
        <step id="S4">User Enables Step Counter</step>
        <step id="S5">Alfred Initiates Step Counting</step>
        <step id="S6">User Walks, Alfred Counts Steps</step>
        <step id="S7">Software Sends Daily Step Data to Health Monitoring Service, which Acknowledges Receipt</step>
        <step id="S8">Caregiver Requests Step Count Data from Alfred</step>
        <step id="S9">Alfred Retrieves Step Data from Software</step>
        <step id="S10">Software Requests User's Step Data from Health Monitoring Service</step>
        <step id="S11">Health Monitoring Service Sends Step Data to Software</step>
        <step id="S12">Alfred Displays Step Data</step>
        <step id="S13">Alfred Shows Step Data to Caregiver</step>
    </mainSequence>
</useCase>
