<useCase id="UC001">
    <name>View Permissions on Objects</name>
    <actors>
        <actor>Curator</actor>
    </actors>
    <preconditions>
        <precondition>The curator is logged in and wants to view permissions on objects.</precondition>
    </preconditions>
    <trigger>User requests to view permissions on objects.</trigger>
    <mainSequence>
        <step id="S1">Curator requests to view permissions.</step>
        <step id="S2">UI validates curator session.</step>
        <step id="S3">Curator session is validated.</step>
        <step id="S4">UI requests object permissions for curator.</step>
        <step id="S5">Permission Service queries permissions by curator ID.</step>
        <step id="S6">Database returns permissions data.</step>
        <step id="S7">Permissions data is processed.</step>
        <step id="S8">UI displays formatted permissions data.</step>
        <step id="S9">Permissions Display shows permissions overview to Curator.</step>
    </mainSequence>
</useCase>
