<useCase id="UC001">
    <name>Update Receptionist Information</name>
    <actors>
        <actor>Admin</actor>
    </actors>
    <mainSequence>
        <step id="S1">Admin requests to update receptionist information.</step>
        <step id="S2">UI shows update form.</step>
        <step id="S3">Router calls Controller to show update form.</step>
        <step id="S4">Controller fetches receptionist data from Repository.</step>
        <step id="S5">Repository retrieves receptionist data from Database.</step>
        <step id="S6">Controller displays update form with current data.</step>
        <step id="S7">Admin fills in updated receptionist details and submits.</step>
        <step id="S8">UI sends updated data to Router.</step>
        <step id="S9">Router calls Controller to update receptionist.</step>
        <step id="S10">Controller saves the updated receptionist data in the Repository.</step>
        <step id="S11">Repository updates receptionist data in the Database.</step>
        <step id="S12">Controller confirms successful update.</step>
        <step id="S13">Router responds with 200 OK (receptionist updated).</step>
        <step id="S14">UI displays success message (receptionist updated).</step>
    </mainSequence>
</useCase>
