<useCase id="UC1">
    <name>Packaging Process</name>
    <actors>
        <actor>Dataset Developer</actor>
        <actor>Archetype Tool</actor>
        <actor>Dataset Repository</actor>
        <actor>Build System</actor>
        <actor>Application Ecosystem</actor>
    </actors>
    <mainSequence>
        <step id="S1">Request to create dataset package by Dataset Developer</step>
        <step id="S2">Generate dataset template by Archetype Tool</step>
        <step id="S3">Provide dataset template to Dataset Developer</step>
        <step id="S4">Define dataset type (Schemas, Configurations, Code) by Dataset Developer</step>
        <step id="S5">Upload dataset package by Dataset Developer</step>
        <step id="S6">Validate package integrity and compatibility by Build System</step>
        <step id="S7">Store validated dataset package in Dataset Repository</step>
        <step id="S8">Acknowledge storage to Build System</step>
        <step id="S9">Notify successful packaging and storage to Dataset Developer</step>
        <step id="S10">Deploy dataset type for app integration by Dataset Developer</step>
        <step id="S11">Integrate dataset type in Application Ecosystem</step>
        <step id="S12">Confirm successful deployment and integration to Dataset Developer</step>
    </mainSequence>
</useCase>
