<useCase id="UC001">
    <name>Remove Audio Effect</name>
    <actors>
        <actor>User</actor>
    </actors>
    <trigger>User selects to remove an audio effect</trigger>
    <mainSequence>
        <step id="S1">User selects the audio effect removal option</step>
        <step id="S2">Dropdown menu is activated displaying effect removal options</step>
        <step id="S3">Dropdown menu directs to close the effect removal panel</step>
        <step id="S4">Audio effect action triggers the removal of the selected effect</step>
        <step id="S5">Audio effect saga initiates the removal saga process</step>
        <step id="S6">Event emitter emits 'EFFECT_DELETE_EFFECT' event</step>
        <step id="S7">Audio controller removes the effect from the audio</step>
        <step id="S8">Dropdown menu removes the selected audio effect removal option</step>
    </mainSequence>
</useCase>
