<useCase id="UC1">
    <name>Requisitar uma tarefa</name>
    <actors>
        <actor>Utente</actor>
        <actor>robDroneGo:robDroneGo</actor>
    </actors>
    <preconditions>
        <precondition>O Utente está autenticado no sistema</precondition>
    </preconditions>
    <successEndConditions>
        <condition>A tarefa foi criada com sucesso</condition>
    </successEndConditions>
    <failureEndConditions>
        <condition>Falha na criação da tarefa</condition>
    </failureEndConditions>
    <mainSequence>
        <step id="S1">O Utente requisita uma tarefa</step>
        <step id="S2">O robDroneGo:robDroneGo solicita o ponto inicial e final da tarefa</step>
        <step id="S3">O Utente insere os dados</step>
    </mainSequence>
</useCase>
