<useCase id="UC1">
    <name>Deploy New App Version with Updated Dataset Type</name>
    <actors>
        <actor>App Developer</actor>
        <actor>Deployment System</actor>
        <actor>Dataset Management</actor>
        <actor>Dataset Type</actor>
        <actor>Dataset Instances</actor>
    </actors>
    <preconditions>
        <precondition>App Developer wants to deploy a new app version with an updated dataset type.</precondition>
    </preconditions>
    <mainSequence>
        <step id="S1">App Developer deploys new app version with updated dataset type.</step>
        <step id="S2">Deployment System checks for updated dataset type.</step>
        <step id="S3">Dataset Management deploys new version of the dataset type.</step>
        <step id="S4">Dataset Type confirms successful deployment of the new version.</step>
        <step id="S5">Dataset Management updates instances to the new dataset type version.</step>
        <step id="S6">Dataset Instances confirm successful update of instances.</step>
        <step id="S7">Dataset Management confirms successful deployment of the app and dataset.</step>
        <step id="S8">Deployment System sends deployment success confirmation to App Developer.</step>
    </mainSequence>
</useCase>
