<useCase id="UC1">
    <name>Update Menu Items</name>
    <actors>
        <actor>Manager</actor>
    </actors>
    <preconditions>
        <precondition>The Manager needs to access the menu management interface.</precondition>
    </preconditions>
    <successEndConditions>
        <condition>The menu items are successfully updated in the database.</condition>
    </successEndConditions>
    <trigger>The Manager selects items to update and submits the updated menu items.</trigger>
    <mainSequence>
        <step id="S1">Manager accesses the Menu Management interface.</step>
        <step id="S2">Management Interface requests current menu items from the Backend Server.</step>
        <step id="S3">Backend Server fetches menu items from the Database.</step>
        <step id="S4">Database provides menu items data to the Backend Server.</step>
        <step id="S5">Backend Server displays menu items to the Management Interface.</step>
        <step id="S6">Manager selects items to update.</step>
        <step id="S7">Manager submits the updated menu items.</step>
        <step id="S8">Management Interface sends an update menu items request to the Backend Server.</step>
        <step id="S9">Backend Server updates menu items in the Database.</step>
        <step id="S10">Database confirms the updated items to the Backend Server.</step>
        <step id="S11">Backend Server confirms successful update to the Management Interface.</step>
        <step id="S12">Management Interface displays a success message to the Manager.</step>
    </mainSequence>
</useCase>
