<useCase id="UC001">
    <name>Manage Service</name>
    <actors>
        <actor>actorName</actor>
    </actors>
    <mainSequence>
        <step id="S1">Actor "actorName" creates a service using CLI by calling caade-service-create()</step>
        <step id="S2">CLI sends a request to caade to create a service by calling service/create()</step>
        <step id="S3">Actor "actorName" creates a service using Web by calling service/create()</step>
        <step id="S4">Web sends a request to caade to create a service by calling service/create()</step>
    </mainSequence>
</useCase>
