<useCase id="UC001">
    <name>Manage-Service</name>
    <actors>
        <actor>actorName</actor>
    </actors>
    <preconditions>
        <precondition>Actor has permission to create service</precondition>
    </preconditions>
    <trigger>actorName triggers the creation of a service</trigger>
    <mainSequence>
        <step id="S1">Trigger the creation of a service using the CLI by calling command caade-service-create()</step>
        <step id="S2">Send the service creation request from CLI to service provider</step>
        <step id="S3">Trigger the creation of a service using the Web interface</step>
        <step id="S4">Request to create a service is sent to service provider via Web interface</step>
    </mainSequence>
</useCase>
