<useCase id="UC001">
    <name>User accesses environment</name>
    <actors>
        <actor>User</actor>
    </actors>
    <mainSequence>
        <step id="S1">User accesses environment</step>
        <step id="S2">Environment Page is accessed</step>
        <step id="S3">Search Service is initiated</step>
        <step id="S4">Search for a task or environment is performed</step>
        <step id="S5">Task or environment data is returned</step>
        <step id="S6">Result Page is shown</step>
        <step id="S7">User views results</step>
        <step id="S8">User accesses task or environment</step>
    </mainSequence>
</useCase>
