<useCase id="UC001">
    <name>Create Build</name>
    <actors>
        <actor>DevSecOpsManager</actor>
    </actors>
    <mainSequence>
        <step id="S1">DevSecOpsManager initiates the creation of a build.</step>
        <step id="S2">DevSecOpsManager instructs the DevSecOpsManager to create a build with name 'hello' and file './templates/build.yml'.</step>
        <step id="S3">The provisioner receives the request to create the build.</step>
        <step id="S4">The provisioner creates the build with the specified details.</step>
        <step id="S5">The build creation is acknowledged by EventBus.</step>
    </mainSequence>
</useCase>
