<useCase id="1">
    <name>Theater Ticket Booking</name>
    <description>Allows users to book theater tickets online</description>
    <actors>
        <actor>User</actor>
        <actor>Theater</actor>
        <actor>Server</actor>
    </actors>
    <preconditions>
        <precondition>System is operational</precondition>
        <precondition>User is authenticated</precondition>
    </preconditions>
    <successEndConditions>
        <condition>User receives confirmation of ticket booking</condition>
    </successEndConditions>
    <trigger>User initiates the process of booking a theater ticket</trigger>
    <mainSequence>
        <step id="S1">User inserts card</step>
        <step id="S2">User selects date for the performance</step>
        <step id="S3">Theater offers available seat</step>
        <step id="S4">User submits the order with seat selection</step>
        <step id="S5">Theater submits the order to Server</step>
        <step id="S6">Server confirms the order</step>
        <step id="S7">Theater confirms the order to User</step>
    </mainSequence>
</useCase>
