<useCase id="UC001">
    <name>Creating a Post-It</name>
    <actors>
        <actor>Client</actor>
        <actor>Server</actor>
    </actors>
    <trigger>canCreatePostIt()</trigger>
    <mainSequence>
        <step id="S1">Client triggers the creation of a new post-it.</step>
        <step id="S2">Server validates the client's request and confirms the user has permission to create post-its.</step>
        <step id="S3">Client sends the necessary information to create the post-it:</step>
        <step id="S4">- Board title</step>
        <step id="S5">- Position in board to create Post-It</step>
        <step id="S6">- Content of Post-It</step>
        <step id="S7">Server processes the received information and creates the post-it.</step>
        <step id="S8">Server sends an acknowledgment code back to the client.</step>
    </mainSequence>
</useCase>
