<useCase id="UC1">
    <name>Piedra, Papel, Tijera Game</name>
    <actors>
        <actor>User</actor>
        <actor>HomeRock</actor>
        <actor>GameMode</actor>
    </actors>
    <preconditions>
        <precondition>HomeRock component is rendered</precondition>
    </preconditions>
    <successEndConditions>
        <condition>Game mode is set to either 'single' or 'multi'</condition>
    </successEndConditions>
    <failureEndConditions>
        <condition>User goes back to the Home screen</condition>
    </failureEndConditions>
    <mainSequence>
        <step id="S1">User renders the HomeRock component</step>
        <step id="S2">HomeRock displays the title "Piedra, Papel, Tijera"</step>
        <step id="S3">User clicks the "Un Jugador" button</step>
        <step id="S4">HomeRock sets the game mode to 'single'</step>
        <step id="S5">User clicks the "Dos Jugadores" button</step>
        <step id="S6">HomeRock sets the game mode to 'multi'</step>
        <step id="S7">User clicks the "Back to Home" button</step>
        <step id="S8">HomeRock triggers the onBackToHome event</step>
    </mainSequence>
</useCase>
