<useCase id="UC1">
    <name>Register Vehicle</name>
    <actors>
        <actor>Administrator</actor>
    </actors>
    <mainSequence>
        <step id="S1">Administrator creates a new instance of Agencia.</step>
        <step id="S2">Administrator creates a new instance of Furgoneta with specified attributes.</step>
        <step id="S3">Furgoneta creates a new instance of Vehiculo.</step>
        <step id="S4">Administrator creates a new instance of Blindado.</step>
        <step id="S5">Administrator creates a new instance of Premium.</step>
        <step id="S6">Administrator creates a new instance of Coche with specified attributes.</step>
        <step id="S7">Administrator registers the Coche vehicle with the Agencia.</step>
        <step id="S8">Agencia adds the Coche vehicle to its list of vehicles.</step>
    </mainSequence>
</useCase>
