<useCase id="UC001">
	<name>Grant Embargo Privileges</name>
	<actors>
		<actor>Digital Records Archivist</actor>
	</actors>
	<preconditions>
		<precondition>Archivist is authenticated</precondition>
	</preconditions>
	<mainSequence>
		<step id="S1">Authenticate with Authentication System</step>
		<step id="S2">Access User Management in EDRMS Core</step>
		<step id="S3">Retrieve User List from User Management DB</step>
		<step id="S4">Display Users in EDRMS Core</step>
		<step id="S5">Select Repository Administrator(s)</step>
		<step id="S6">Request to Update Privileges in Access Control Module</step>
		<step id="S7">Grant Embargo Privileges in User Management DB</step>
		<step id="S8">Update Confirmation in EDRMS Core</step>
	</mainSequence>
</useCase>
