<useCase id="10060">
    <name>Bereitstellung eines Messenger-Service für eine Organisation</name>
    <actors>
        <actor>Org-Admin</actor>
    </actors>
    <mainSequence>
        <step id="S1">Mit einem Admin-Account am Registrierungs-Dienst anmelden</step>
        <step id="S2">Messenger Service erstellen</step>
        <step id="S3">Prüfung auf zulässigen Domainnamen</step>
        <step id="S4">Starte neuen Messenger-Service für die Organisation mit Matrix-Domain</step>
        <step id="S5">Initial einrichten des Messenger-Service</step>
        <step id="S6">Föderationsliste aktualisieren</step>
    </mainSequence>
</useCase>
