<useCase id="UC001">
    <name>View System Messages</name>
    <actors>
        <actor>End User</actor>
    </actors>
    <preconditions>
        <precondition>The user has the app opened.</precondition>
    </preconditions>
    <successEndConditions>
        <condition>The user can view system messages and message details.</condition>
    </successEndConditions>
    <trigger>The user opens the system message module in the app.</trigger>
    <mainSequence>
        <step id="S1">User opens the mobile app.</step>
        <step id="S2">App loads the system message module.</step>
        <step id="S3">App requests system message data retrieval.</step>
        <step id="S4">System message module checks for unread messages and retrieves them.</step>
        <step id="S5">App displays unread message notification to the user.</step>
        <step id="S6">User taps to view the messages.</step>
        <step id="S7">User views message details.</step>
        <step id="S8">App requests message content.</step>
        <step id="S9">System message module fetches the message content.</step>
        <step id="S10">App displays the content to the user.</step>
    </mainSequence>
</useCase>
