<useCase id="UC1">
    <name><![CDATA[Manage-Applications]]></name>
    <actors>
        <actor>A</actor>
    </actors>
    <mainSequence>
        <step id="S1">Actor "A" initiates Edgeville-analytics-run() function.</step>
        <step id="S2">CLI executes analytics/run() for managing applications.</step>
        <step id="S3">Actor "A" triggers analytics/run() through Web interface.</step>
        <step id="S4">Web executes analytics/run() for application management.</step>
    </mainSequence>
</useCase>
