<useCase id="UC01">
  <name>Selecting Data Source Name</name>
  <description>Data steward selects 'data/source/name' from Common Data Service</description>
  <actors>
    <actor>Data Steward</actor>
  </actors>
  <preconditions>
    <precondition>Data Steward has access to the Common Data Service</precondition>
  </preconditions>
  <successEndConditions>
    <condition>The selected 'data/source/name' is successfully egressed from the Common Data Service</condition>
  </successEndConditions>
  <failureEndConditions>
    <condition>The 'data/source/name' selection process failed</condition>
  </failureEndConditions>
  <trigger>Data Steward decides to select 'data/source/name' from Common Data Service</trigger>
  <mainSequence>
    <step id="S1">Data Steward selects 'data/source/name' from Common Data Service</step>
    <step id="S2">Egressed data is displayed to the Data Steward</step>
  </mainSequence>
</useCase>
